{"cameraMode":{"drawMode":0,"name":"Shaded","section":"Shading Mode"},"sceneLighting":false,"audioPlay":false,"sceneViewState":{"showFog":true,"showMaterialUpdate":false,"showSkybox":false,"showFlares":true,"showImageEffects":true,"showParticleSystems":true},"in2DMode":false,"pivot":{"x":-0.027041345834732057,"y":1.9862415790557862,"z":-0.00005879625678062439},"rotation":{"x":-0.2258644700050354,"y":-0.037404708564281467,"z":0.008679425343871117,"w":-0.9734081625938416},"size":0.6819824576377869,"orthographic":false}